{"action_index.md":"e767105f","algolia_index.md":"f8ba1501","cli_index.md":"1388c584","code_index.md":"2b45a506","create-custom-app_index.md":"c1c59d27","index.md":"338ce195","interview_index.md":"b3c63001","summary_css_1px.md":"c8f9d1af","summary_css_bfc.md":"47c81c7d","summary_css_box-model.md":"6a2a190d","summary_css_center.md":"03913b8f","summary_css_flex.md":"160fee65","summary_css_grid.md":"48ed1fb5","summary_css_heart.md":"b20d6bfc","summary_css_preprocessor.md":"5037cd81","summary_css_reflow-repaint.md":"269b0de4","summary_css_selector.md":"7ede321a","summary_engineered_module-federation.md":"e2973904","summary_engineered_monorepo-workspace.md":"18d0e27d","summary_engineered_node_modules.md":"6d0691ca","summary_engineered_npm-yarn-pnpm.md":"bb36ac57","summary_engineered_web-component.md":"b0c5d0a4","summary_javascript_es6.md":"bb60aab2","summary_javascript_pwa-serviceworker.md":"76267f26","summary_javascript_promise.md":"24851a97","summary_javascript_webworker.md":"8490d9c6","summary_javascript_call-apply-bind.md":"ae63471a","summary_javascript_closure.md":"0fa6b7b4","summary_javascript_context.md":"0222fd7d","summary_javascript_cookie-session-localstorage.md":"aed1298f","summary_javascript_event-loop.md":"e21c4c4d","summary_javascript_instanceof.md":"85f8f2b3","summary_javascript_new.md":"39207ca0","summary_javascript_prototype-chain.md":"d8273446","summary_javascript_types.md":"4e691285","summary_network_ajax.md":"b744a31d","summary_network_http-status-code.md":"2db02491","summary_other_url-to-display.md":"d3c81e80","summary_typescript_types.md":"bb368895","summary_vue_computed-watch.md":"42938f3d","summary_vue_lifecycle.md":"ea53fe3d","summary_vue_mvvm.md":"eef11c52","summary_vue_reactivity.md":"1cb4da80","summary_vue_vue-router.md":"551d0180","summary_index.md":"0cdb9017"}
