{"achieve_extension_index.md":"lHxEU9D4","summary_api_message-channel.md":"DbL8B5ws","summary_browser_reflow-repaint.md":"ucP3_RH4","summary_other_encryption.md":"15AgorkI","achieve_algolia_index.md":"ClTFt9Yu","summary_nginx_index.md":"D3us9iN1","summary_nodejs_deno.md":"CjyXGjjD","summary_network_http.md":"RuLQUwRL","summary_other_babel.md":"CsYPQ-Q8","summary_nodejs_dirname.md":"NxmVSqmC","summary_other_canvas.md":"ccKJ00OZ","code_animation_canvas.md":"BV38cJN1","summary_other_lazy-pre-load.md":"cUJ7Xg4l","summary_engineered_module-federation.md":"NJH60mum","summary_other_shadow-dom.md":"Bk3RsVC3","summary_other_jwt.md":"1-Iegwpv","achieve_menu-generator_index.md":"BFGzf77d","summary_other_ssr.md":"C1nxN6M7","summary_other_virtual-dom.md":"Bt3y6KRY","summary_react_suspense.md":"BzOjYm8Q","summary_security_csrf.md":"Dy7dFMe1","summary_security_clickjacking.md":"DJ9qGUyX","summary_engineered_module.md":"5lzpZ56L","summary_security_middle-attack.md":"DxutZCxI","summary_security_xss.md":"D2VidQ9V","summary_engineered_monorepo-workspace.md":"es6F8nUQ","summary_ts_interface.md":"DbVoDkOy","summary_ts_types.md":"-38Yc1f7","summary_engineered_node_modules.md":"BpHIWAs_","summary_engineered_npm-yarn-pnpm.md":"BpCod14t","summary_engineered_pwa.md":"D9UDChUh","summary_vue_01.md":"BmYEkpAD","summary_vue_component-communication.md":"B3O8YNgF","code_vue_hooks.md":"xbrf_nJ5","summary_js_prototype-chain.md":"E7lWBnsx","summary_vue_computed-watch.md":"rqDgnfJg","summary_vue_keep-alive.md":"BVzvwQwN","summary_vue_lifecycle.md":"wNQKSLcG","summary_vue_diff.md":"DFgFUBPU","summary_vue_nexttick.md":"Ct45DkoG","summary_vue_mvvm.md":"De1DXFGG","summary_vue_key.md":"i_X-aWQ5","summary_vue_store.md":"DkXRcdGh","summary_vue_reactivity.md":"Dc-TQiG-","summary_vue_template.md":"t7hd583P","summary_css_flex.md":"CZprFQ-Z","summary_network_01.md":"CxSqcvyG","achieve_action_index.md":"NxrVg5DM","todo_index.md":"BUhH2-Kg","summary_engineered_01.md":"I6-JWO41","summary_css_box-model.md":"BiCHi4Af","summary_vue_vue-router.md":"Bz2LIaGU","summary_bundler_other.md":"RKYAAssY","summary_js_arrow-function.md":"D8uMbkZo","summary_js_call-apply-bind.md":"DNhIcSYo","summary_js_closure.md":"Cr63pO-h","summary_js_context.md":"COvTjwkd","summary_js_ecmascript.md":"D0EBqTb_","summary_network_domain-site.md":"Wlw0iEJD","summary_network_http-code.md":"BQAK0ZTo","summary_bundler_webpack.md":"BwqE3PXz","code_index.md":"B7DQQt0A","summary_js_fast-slow-properties.md":"B0hX_L_G","summary_css_layout.md":"CDSI2oFG","summary_js_generator.md":"DPiR3X6i","code_js_utils.md":"D355bonF","code_nodejs_file.md":"B89kkNX1","summary_js_types.md":"DoeWc_1x","summary_js_new.md":"SEZ2eiLO","summary_html_attributes.md":"9xcloGD5","achieve_create-custom-app_index.md":"CbHUtSl1","summary_css_1px.md":"BpFmG6W5","summary_css_center.md":"Di1t6EJY","summary_css_bem.md":"BHXunSGH","summary_browser_browser-cache.md":"BhwfJ2Hn","summary_js_promise.md":"fKA79ySq","code_js_array.md":"DsSm9V94","summary_js_inherit.md":"DTcLhpPM","code_command_command.md":"rvsFkgQ-","summary_css_pseudo.md":"DMEJc2lT","summary_js_instanceof.md":"CMI2Dl_w","summary_browser_event-flow.md":"w03TB7w8","code_vite_plugin.md":"CFslYyYm","summary_browser_url-to-display.md":"teejjegw","summary_css_grid.md":"bu2NA8rE","summary_js_event-loop.md":"BGtBqQOc","code_js_reg.md":"Dztt9Xyg","achieve_cli_index.md":"Bijji7X9","summary_html_link.md":"Bk7i13EV","summary_algorithm_sort.md":"wKAlw9Pn","summary_network_ajax.md":"BzVUM4gS","summary_css_selector.md":"Bgq8TFuK","summary_api_web-worker.md":"v5GIpcCI","index.md":"D8o-XhAw","summary_api_beacon.md":"DOFPYqgb","achieve_awesome-version_index.md":"Baa7K3mY","summary_browser_cache.md":"Cx1ilFNJ","interview_hidden.md":"oZaRs-sZ","interview_index.md":"KRyflkTi","summary_algorithm_01.md":"D-uEloaT","summary_browser_engine.md":"CUWX6hDQ","summary_browser_process.md":"imtqW3-K","summary_api_observers.md":"JEZBliGs","summary_api_service-worker.md":"D9frme65","summary_api_web-socket.md":"CT-y4bR6","summary_network_cross-domain.md":"DxBx2Z85","summary_api_sse.md":"DgGwDJ42","achieve_img-load_index.md":"DfDnBCPp","summary_api_web-component.md":"DAhfuJkr","summary_css_bfc.md":"tfWLRXON","summary_engineered_micro-frontend.md":"B-nqQDDD","summary_other_virtual-list.md":"81nxYiSO","summary_pattern_pub-sub.md":"DEwRaR_n","achieve_decorator_index.md":"CHl8sOxo","summary_bundler_vite.md":"B3HkVTR0","summary_js_functional.md":"C0gqKciL","achieve_slide-in_index.md":"DiPaZZUe","summary_other_web-assembly.md":"Cz-JDwcX","summary_js_gc.md":"DPu4mXYB","summary_pattern_observe.md":"DaaqXlwT","summary_react_fiber.md":"BIYjyGV2","summary_react_hooks.md":"DcTleqGy","summary_html_meta.md":"BbmBKatZ","summary_react_lifecycle.md":"BPUS6CSx","summary_js_array.md":"kkKi0Atg","summary_index.md":"Bdqq6jLm","summary_html_script.md":"BySs3Fkv","summary_css_preprocessor.md":"D-sRoiyB","achieve_bpmn-js_index.md":"BSqthGe4","summary_js_number.md":"BaY2s-EC","summary_network_http-header.md":"DxcYKKjy","summary_browser_performance.md":"IQKJEgG4"}
