{"achieve_action_index.md":"a89ca88f","summary_engineered_01.md":"14168938","interview_hidden.md":"8f9a7c44","code_javascript_array.md":"7c30909e","code_javascript_reg.md":"bd0c3eba","code_javascript_utils.md":"b9fdfc78","code_nodejs_file.md":"83732620","summary_css_center.md":"0bf28abc","summary_css_flex.md":"4d99518c","summary_css_grid.md":"80a01e07","summary_css_layout.md":"3876e88e","summary_css_preprocessor.md":"cd6a89c5","summary_css_pseudo.md":"07fdded6","summary_css_selector.md":"a8ce6df6","achieve_extension_index.md":"170ef9ae","code_vite_plugin.md":"16c79564","code_vue_hooks.md":"5bb4b9bf","code_index.md":"75d9c7fe","index.md":"392a3c4c","summary_bundler_other.md":"e215b835","interview_index.md":"0f22f6be","code_animation_canvas.md":"059f2cb2","summary_algorithm_sort.md":"f72b6a87","summary_browser_browser-cache.md":"5bdbe727","summary_browser_cache.md":"7fa7b339","summary_browser_event-flow.md":"1ee40037","summary_browser_performance.md":"bd7c814f","summary_browser_reflow-repaint.md":"216b9626","summary_browser_rel.md":"8a026cda","summary_browser_script.md":"a140f69e","summary_browser_url-to-display.md":"62c4467b","summary_css_bem.md":"0e47dc0d","achieve_img-load_index.md":"82e40a96","achieve_cli_index.md":"e68cdfd1","achieve_menu-generator_index.md":"8b645cb8","summary_bundler_vite.md":"43ff18bd","achieve_algolia_index.md":"02fcd733","summary_browser_engine.md":"8127e1cf","code_command_command.md":"ef7f4daa","summary_browser_process.md":"335a0160","summary_other_lazy-pre-load.md":"5b5ca054","summary_engineered_micro-frontend.md":"8f450553","summary_engineered_monorepo-workspace.md":"3a9fd553","summary_engineered_node_modules.md":"f80a5a21","summary_engineered_npm-yarn-pnpm.md":"2bef6cc2","summary_engineered_web-component.md":"35f591cf","summary_index.md":"e899592b","summary_js_array.md":"fe59dbb6","summary_js_arrow-function.md":"8d299797","summary_engineered_module-federation.md":"ec858cbf","summary_js_fast-slow-properties.md":"7f771fb4","summary_js_functional.md":"7102305b","summary_js_call-apply-bind.md":"059ecfa3","summary_js_gc.md":"d2d750c4","summary_js_closure.md":"89c1985d","summary_js_inherit.md":"34990a3d","summary_js_number.md":"2a58258a","summary_js_prototype-chain.md":"d5e067e0","summary_js_context.md":"4b0ae43f","summary_js_instanceof.md":"76ed59c9","summary_network_01.md":"7b1fb82b","summary_network_ajax.md":"c9f83a2b","summary_js_event-loop.md":"b0d85e3e","summary_js_ecmascript.md":"0d3c8ad0","summary_network_cross-domain.md":"d55123f2","summary_network_domain-site.md":"c2f4b649","summary_js_new.md":"a855cfaa","summary_network_http-code.md":"df1d6fbc","summary_network_web-socket.md":"13c5eb63","summary_nginx_index.md":"6438da2c","summary_js_promise.md":"746c7e56","summary_engineered_module.md":"9b78d4cf","summary_js_pwa-serviceworker.md":"3e374f40","summary_nodejs_dirname.md":"84ae92e5","summary_js_webworker.md":"577f47de","summary_other_virtual-dom.md":"c60d3089","summary_other_virtual-list.md":"e09fa415","summary_other_web-assembly.md":"5d0c757a","summary_pattern_observe.md":"173ab07a","summary_react_lifecycle.md":"c1cb7cdc","summary_react_suspense.md":"2dfb573c","summary_react_use-callback.md":"e706e86a","summary_react_use-memo.md":"02d299ec","summary_security_clickjacking.md":"07ee413f","summary_security_csrf.md":"b9c0ff3e","summary_security_middle-attack.md":"0870046e","summary_security_xss.md":"c6285ea3","summary_network_http.md":"b852ccd1","summary_ts_interface.md":"0c50b932","summary_network_sse.md":"b325f1fa","summary_ts_types.md":"53d8b019","summary_vue_vue-router.md":"1dc9dbf6","summary_network_http-header.md":"2758535c","summary_vue_01.md":"600301f0","summary_vue_component-communication.md":"de4acfa7","summary_css_box-model.md":"2d11e3ea","summary_vue_diff.md":"4535c1bc","summary_vue_keep-alive.md":"3c893d71","summary_css_1px.md":"348bcfc8","summary_js_generator.md":"19e3af80","summary_vue_key.md":"e0d3ab5a","achieve_create-custom-app_index.md":"d9894315","summary_vue_lifecycle.md":"2d279ef5","summary_nodejs_deno.md":"972ece67","summary_vue_mvvm.md":"f812c59a","summary_other_canvas.md":"285f9d06","achieve_bpmn-js_index.md":"80268286","summary_vue_nexttick.md":"e9af7104","summary_vue_reactivity.md":"9cf0d527","summary_algorithm_01.md":"ddba7aea","achieve_decorator_index.md":"6489172b","summary_js_types.md":"356b6af1","summary_vue_template.md":"9e47cf25","summary_css_bfc.md":"b80b650e","todo_index.md":"aeec4c24","summary_other_shadow-dom.md":"72723876","summary_other_ssr.md":"8307b0ed","summary_bundler_webpack.md":"f52c32e5","summary_pattern_pub-sub.md":"dc130102","summary_react_fiber.md":"7f84d6f9","summary_vue_computed-watch.md":"ae5d761b","summary_vue_store.md":"006b640c","summary_other_encryption.md":"4e293b01","summary_other_babel.md":"578e17ea"}
