{"code_javascript_array.md":"686f95c2","achieve_action_index.md":"adfa9ddf","achieve_algolia_index.md":"b953d11c","achieve_cli_index.md":"4ac11770","achieve_create-custom-app_index.md":"218b1a14","summary_javascript_cookie-storage.md":"f4ca308c","code_nodejs_file.md":"d1c145eb","code_index.md":"87af3baf","index.md":"6170f452","interview_index.md":"e4ff6a0a","summary_algorithm-datastructure_01.md":"60ee8906","summary_algorithm-datastructure_array-linkedlist.md":"a67231ad","summary_bundler_other.md":"861918f0","summary_bundler_vite.md":"7e814d33","summary_css_box-model.md":"5042ef5f","summary_css_center.md":"5c2a6c2a","summary_css_flex.md":"eb18a2de","achieve_menu-generator_index.md":"c490ca5e","summary_css_preprocessor.md":"d59e101a","summary_css_selector.md":"f89a2523","summary_engineered_module-federation.md":"d968fdd0","summary_engineered_node_modules.md":"633574ea","summary_engineered_npm-yarn-pnpm.md":"adc03787","summary_engineered_web-component.md":"30df8ef1","summary_javascript_arrow-function.md":"8c352c2b","summary_javascript_call-apply-bind.md":"74da2f39","achieve_extension_index.md":"b78dbbcc","summary_css_grid.md":"c2563d34","code_animation_canvas.md":"1e0f84ab","summary_css_reflow-repaint.md":"4bdb17ff","code_javascript_utils.md":"02839bd2","code_javascript_reg.md":"fa33ab01","code_command.md":"70629a85","summary_javascript_closure.md":"7e69bc43","summary_algorithm-datastructure_sort.md":"9286b687","summary_javascript_context.md":"69766d18","summary_javascript_event-loop.md":"6cab5d5c","summary_engineered_module.md":"7f96d710","summary_javascript_instanceof.md":"e4157afd","achieve_decorator_index.md":"3b9c8aaa","summary_engineered_monorepo-workspace.md":"ea834361","summary_vue_keep-alive.md":"1bfecb35","achieve_bpmn-js_index.md":"a3fbfd29","summary_bundler_webpack.md":"e39b3513","summary_network_http-status-code.md":"cc41a5ce","summary_network_http.md":"766a1553","summary_nodejs_deno.md":"d119c19a","summary_nodejs_dirname.md":"4fb3f224","summary_other_webassembly.md":"df7ca8fb","summary_other_event-flow.md":"a73b392c","summary_other_fast-slow-properties.md":"0d42bc35","summary_other_gc.md":"ec929123","summary_other_lazy-pre-load.md":"b32c891b","summary_other_url-to-display.md":"00f63b65","summary_pattern_observe.md":"6d4301b1","summary_pattern_pub-sub.md":"71d2a161","summary_security_xss-csrf.md":"342f452b","summary_typescript_types.md":"a61fa862","summary_vue_component-communication.md":"3cc4f55b","summary_vue_lifecycle.md":"e2d8f201","summary_vue_mvvm.md":"f1f6fc3a","summary_vue_nexttick.md":"2b9b912a","summary_vue_reactivity.md":"85e21848","summary_vue_store.md":"9d1b0c46","summary_vue_vue-router.md":"0f28e1d7","summary_index.md":"1a9bd4ed","todo_index.md":"bcbe77ce","summary_vue_key.md":"e75c5ffd","summary_javascript_es6.md":"4c34be3c","summary_javascript_new.md":"488db63b","summary_vue_computed-watch.md":"b7c39534","summary_vue_diff.md":"9e837f02","summary_javascript_webworker.md":"62870d63","summary_css_1px.md":"ad98edce","summary_css_bem.md":"835dfc3a","summary_css_bfc.md":"79bec38d","summary_javascript_promise.md":"7c39ea3d","summary_javascript_prototype-chain.md":"3aa8a8cc","summary_javascript_pwa-serviceworker.md":"58556004","summary_javascript_types.md":"9ea82bfc","summary_network_ajax.md":"d20b7ec2","summary_network_browser-cache.md":"ff097fbe","summary_network_domain-site.md":"f1219564"}
